{
  "codex_section": "analysis_directives.soft_outcome_distinction",
  "call_ids": [
    "10000793851",
    "10000811924",
    "30000715604",
    "SESSION10_06b53b82",
    "SESSION10_0f86f9a0",
    "SESSION10_5fc79d73",
    "SESSION12_93ede28c",
    "SESSION12_9746e9d8",
    "SESSION14_444221f1",
    "SESSION14_b1e8ab55",
    "SESSION16_da8e5ba6",
    "SESSION17_5fe4121d",
    "SESSION20_1a3a7be3",
    "SESSION23_9b81d10b",
    "SESSION24_9420d5ec",
    "SESSION26_7fdc3074",
    "SESSION26_a514d830",
    "SESSION2_77086e3f",
    "SESSION4_3cbbfe29",
    "SESSION4_690e690d",
    "SESSION8_006236ee",
    "SESSION8_c1f36478",
    "SESSION8_e3ceb903",
    "SESSION9_6504f4b1"
  ],
  "pattern_counts_by_classification": {
    "conditional_booking": 16,
    "other": 8,
    "micro_trade": 1
  },
  "recent_examples": [
    {
      "call_id": "SESSION2_77086e3f",
      "ts": "04:46",
      "quote": "Thursday evening? K. So maybe I'll if I don't hear from you, maybe I'll just follow-up on Friday. Would that work?",
      "classification": "conditional_booking"
    },
    {
      "call_id": "SESSION4_3cbbfe29",
      "ts": "02:37",
      "quote": "I'll make a note here to follow-up with you in a couple of months just to see where everything's kind of at, but I'll take you off our list for now.",
      "classification": "other"
    },
    {
      "call_id": "SESSION4_690e690d",
      "ts": "02:25",
      "quote": "I can reach out to my design team and see if they would be able to do anything. And then if they can, I'll give you a callback, and we could totally get you scheduled. Okay?",
      "classification": "conditional_booking"
    },
    {
      "call_id": "SESSION8_006236ee",
      "ts": "00:51",
      "quote": "Around 12:00 work for you?",
      "classification": "conditional_booking"
    },
    {
      "call_id": "SESSION8_c1f36478",
      "ts": "04:16",
      "quote": "Cool. Well, yeah, I'll make a note and take you out for now. But then, yeah, when we can look out to calling you in a few months or looking out for your call and kinda work with you from there.",
      "classification": "conditional_booking"
    },
    {
      "call_id": "SESSION8_e3ceb903",
      "ts": "05:03",
      "quote": "So I'll I'll I'll message them right now, and then I'll give you a callback with an update later. Does that work for you?",
      "classification": "conditional_booking"
    },
    {
      "call_id": "SESSION9_6504f4b1",
      "ts": "01:35",
      "quote": "they can call me back tomorrow if they want, and I can check my schedule to see if",
      "classification": "conditional_booking"
    },
    {
      "call_id": "SESSION9_6504f4b1",
      "ts": "01:41",
      "quote": "I hate to set it up until they set the schedule on Friday, to make sure I'm gonna be off.",
      "classification": "conditional_booking"
    }
  ],
  "outcomes": {
    "null": 25
  },
  "gray_matter_exemplars": [],
  "last_updated_at": "2026-05-23T04:47:15.000211Z"
}