{
  "codex_section": "button_up.required_elements.text_followup_promise",
  "call_ids": [
    "SESSION18_42790988"
  ],
  "pattern_counts_by_classification": {
    "micro_trade": 1
  },
  "recent_examples": [
    {
      "call_id": "SESSION18_42790988",
      "ts": "01:14",
      "quote": "I'll I'll get that set up, and we will shoot you a text just to double check that time still works for you. So, Sebastian's not popping up out of the blue for you.",
      "classification": "micro_trade"
    }
  ],
  "outcomes": {
    "null": 1
  },
  "gray_matter_exemplars": [],
  "last_updated_at": "2026-05-23T04:47:15.002546Z"
}