{
  "verdict": "revisions_required",
  "fabricated_quotes": 3,
  "weak_reasoning": 6,
  "revision_summary": "Four targeted fixes required before Stage 3 is production-ready:\n\n1. TRAJECTORY SHAPE LABEL: Change 'stagnant' to 'ascending' for the customer trajectory. Add a separate note that rep strategy was reactive/flat throughout. The current label contradicts Stage 3's own state_changes evidence and will confuse managers.\n\n2. SPEAKER ATTRIBUTION FLAG: The starting_state quote ('Hey. Doing good, Bucky. How are you, man?') appears in speaker_1's Deepgram block, not speaker_2's. Stage 3 must flag this transcription ambiguity rather than treating it as a clean customer quote. The warmth conclusion can stand but must be grounded in the customer's behavior throughout the call (cooperative responses, proactive scheduling offer) rather than a potentially mis-attributed quote.\n\n3. CODEX REFERENCE CORRECTIONS: (a) cherry_pick_moments[2] (02:39): Replace curiosity_over_features reference with bill_anchoring — the actual gap is the absence of a bill-tieback in the explanation, not unprompted feature-selling. The customer asked a direct question; the anti-pattern doesn't apply. (b) cherry_pick_moments[3] (05:39): Soften the codex citation — the button_up protocol requires phone to be specified, not that in-person must be excluded. Frame the coaching implication as inference, not direct codex prohibition.\n\n4. MISSED VERIFY ITEMS: Add a cherry_pick moment for the missing interest_in_solar verify item (never asked) and the missing prior_designs item. The codex marks interest_in_solar as 'THE EMOTIONAL ANCHOR' with depth_grading:true — its absence is a higher-priority coaching gap than the phone-vs-in-person format question currently in the analysis. Also add the bill-contingent booking risk at 04:19 ('I can schedule you right after you send that') to the handoff_brief.unresolved_concerns, noting the contingency was apparently resolved on-call but should be confirmed.\n\nThe name error classification ('rapport_repair') should also be corrected to 'hygiene_gap' — no repair occurred in the transcript.",
  "flags_count": 3
}