{
  "verdict": "revisions_required",
  "fabricated_quotes": 4,
  "weak_reasoning": 6,
  "revision_summary": "Four targeted fixes required before production:\n\n1. VERIFY COMPLETION GAP — Stage 3 never surfaces that the rep completed approximately 3 of 8 required verify items (codex threshold: 6-of-8). Title/co-owners, residence length, interest in solar, roof type/age, and prior designs were all skipped. This is a significant structural gap that belongs in cherry_pick_moments and coaching_focus. Add a verify_completion_gap cherry_pick moment citing the codex's verify.required_completion_threshold = 6_of_8.\n\n2. CODEX MISUSE ON CROSS-SELL REFERENCE — cherry_pick_moments[1] (07:09 garage) incorrectly cites cross_sell_signals.roof_replacement_planned. Glenn never mentioned needing a roof replacement — his garage roof is already open to the sky. Correct the reference to the TBD solar_for_secondary_structure cross-sell signal and adjust the coaching framing accordingly. The primary classification should be 'handoff_specificity_gap' (closer needs to know the garage is a second installation surface) rather than a setter cross-sell miss.\n\n3. EMPATHY CLASSIFICATION LABEL — cherry_pick_moments[3] is labeled 'empathy_miss' but the rep demonstrably showed empathy (multiple 'oh my gosh' responses, 'thank you for your service'). The actual gap is the missing value bridge, not missing empathy. Relabel as 'empathy_bridge_miss' or 'vulnerability_bridge_gap' to accurately target the coaching. The codex's empathy_on_vulnerability_disclosure section confirms the move is 'empathy + bridge to value' — the empathy was present.\n\n4. $800 AVERAGE ATTRIBUTION — The $800/month average figure used throughout the analysis (handoff_brief, coaching_focus) was stated by the REP (speaker_1 at 08:21: 'So about an $800 a month average'), not by Glenn. Glenn said '$600 to $1,100 a month.' Correct all references to attribute the $800 figure to the rep's inference/summary, not Glenn's stated number. This matters for the closer — Glenn's actual range is $600–$1,100, and the rep's $800 average is an approximation the closer should not treat as Glenn's own framing.\n\nSecondary (lower priority, incorporate if feasible):\n- Add missed_moment for 16:01 ('I prefer mornings because then I could take off to the office') as the specific transcript evidence anchoring the button-up computer/no-driving coaching point — Glenn's own words confirm the risk.\n- Soften 'do not show up without one' in handoff_brief.closer_should_know to align with codex handoff_brief_discipline ('inform but not dictate').\n- Remove the corpus-superlative claim ('most emotionally loaded bill story in this corpus') from coaching_focus[0].why — ungrounded cross-call comparison.",
  "flags_count": 2
}