{
  "verdict": "revisions_required",
  "fabricated_quotes": 3,
  "weak_reasoning": 6,
  "revision_summary": "Three targeted fixes required before Stage 3 is production-ready:\n\n1. CRITICAL FACTUAL ERROR \u2014 handoff_brief.closer_should_know states Joseph 'moved in February.' The transcript shows Joseph initially said February, Jake asked 'I'm sorry. December?' and Joseph confirmed 'Yes.' The confirmed move-in month is December. Fix the handoff brief to read 'moved in December' and audit all other references to the move-in month across the output.\n\n2. MISSED UNRESOLVED SIGNAL \u2014 Joseph says 'Can I verify?' at [01:44] and receives no response. This is an unresolved customer utterance that Stage 3 does not surface anywhere. Add to cherry_pick_moments as an unresolved_signal classification and flag in the handoff_brief under unresolved_concerns: 'Joseph asked to verify something at [01:44] \u2014 unclear what (company identity? address?). Closer should check whether Joseph has any outstanding verification concern at the start of the appointment.'\n\n3. CREDIT QUALIFIER CAPTURE GAP \u2014 Stage 3 surfaces the 760\u2192670 threshold error in cherry_pick_moments[0] but does not flag that Joseph's actual confirmation of the credit threshold is absent from the transcript. The affirmations at [02:45] ('Yes. Yeah. Yes. Okay. Okay. Cool. Cool. Cool.') appear to be Jake's voice, not Joseph's. Add to cherry_pick_moments or coaching_focus: the credit qualifier may be unconfirmed \u2014 the closer should verify credit eligibility has actually been established before proceeding to proposal.\n\nSecondary fix (tone/fabrication): Remove the invented coaching script in cherry_pick_moments[4].stewart_read ('New homeowners are actually some of our best fits \u2014 you're setting up your home from scratch, and locking in your energy costs now means you never have to worry about what Dominion does to your rates'). Replace with intent-and-emotion framing per the schema's numeric_discipline directive: flag the new-homeowner signal as an untapped enthusiasm anchor and note that the specific bridge language should come from Kenny's coaching sessions or Ion-designated exemplar calls.",
  "flags_count": 3
}