{
  "verdict": "revisions_required",
  "fabricated_quotes": 3,
  "weak_reasoning": 5,
  "revision_summary": "Three targeted fixes required before Stage 3 is production-ready:\n\n1. CRITICAL — Diarization misattribution: The 'What do you want?' fragment at 00:07 is almost certainly the customer's voice mis-attributed to speaker_1 by Deepgram, not the rep reading a script prompt aloud. The full speaker_1 block at 00:07 includes the form reference ('Just reaching out about the solar form you filled online') and the human pause ('How are you doing?'), which ARE intros.standard success signals. Stage 3 must (a) acknowledge the diarization ambiguity, (b) retract the 'script prompt read aloud / mechanical reading' narrative, (c) revise the intro coaching to focus on the actual observable gaps (hesitant delivery, fragmented pacing, customer comprehension failures) rather than the fabricated script-reading error. This affects rep_intent[0], starting_state.reasoning, cherry_pick_moments[0], multi_touch_patterns[0].stewart_read, and coaching_focus[1].\n\n2. MODERATE — Misclassification of 02:02 as scope creep: The rep's bill-swap reframe ('cheaper than your monthly bill') is not scope creep per the schema definition (which requires quoting prices or savings ranges). It is a bill-swap reframe attempted without a bill anchor — a different and more precise coaching gap. Revise cherry_pick_moments[2] classification and schema_reference to coaching_philosophy.objection_inversion + coaching_philosophy.bill_anchoring, and update the coaching_implication accordingly.\n\n3. MINOR — Tone and speculation: (a) Remove the clinical speculation about the wife's condition ('recurring medical crisis or cognitive episode where she is unresponsive or incapacitated') from cherry_pick_moments[3].stewart_read — the coaching point is valid without the diagnosis. (b) Revise coaching_focus[0].why to remove 'the rep had one job (be human for three seconds) and did not do it' — replace with manager-facing clinical language. (c) Fix cherry_pick_moments[4] classification label from 'conditional_booking' to 'soft_outcome' or 'no_appointment' to match the schema definition.\n\nAdditionally, Stage 3 should add the missed price_estimate_before_design rebuttal scoring at 02:00 and credit the rep's adaptive rephrasing of the utility question at 01:19 as a partial positive to give the brief appropriate balance.",
  "flags_count": 3
}